{
  "version": "48.0.0",
  "files": {
    "e4faa99964770efa9ca9c1813f4ffa7a4d5885bd1ec2b35c303f3c6e02e63f69": {
      "displayName": "NetworkStack Template",
      "source": {
        "path": "NetworkStack.template.json",
        "packaging": "file"
      },
      "destinations": {
        "current_account-current_region-e42ab5e2": {
          "bucketName": "cdk-hnb659fds-assets-${AWS::AccountId}-${AWS::Region}",
          "objectKey": "e4faa99964770efa9ca9c1813f4ffa7a4d5885bd1ec2b35c303f3c6e02e63f69.json",
          "assumeRoleArn": "arn:${AWS::Partition}:iam::${AWS::AccountId}:role/cdk-hnb659fds-file-publishing-role-${AWS::AccountId}-${AWS::Region}"
        }
      }
    }
  },
  "dockerImages": {}
}